{
    "QoL" : {
        "descriptions" : [
            "게임 플레이 변화는 최소한으로 주며 편의성을 개선합니다."
        ]
    },
    "계산" : {
        "descriptions" : [
            "공장의 각종 요소를 계산하는데 도움을 주는 도구 및 인터페이스를 추가합니다."
        ]
    },
    "시각화" : {
        "descriptions" : [
            "특정 요소를 부각 시켜 흐름을 파악하거나 가독성을 높입니다."
        ]
    },
    "그래픽" : {
        "descriptions" : [
            "그래픽의 개선 및 수정이 있습니다."
        ]
    },
    "회로" : {
        "descriptions" : [
            "회로 관련 아이템이나 기능을 추가 및 수정합니다."
        ]
    }
}